modernize_reporter/__init__.py
modernize_reporter/main.py
modernize_reporter-0.3.2.dist-info/METADATA
modernize_reporter-0.3.2.dist-info/RECORD
modernize_reporter-0.3.2.dist-info/WHEEL
modernize_reporter-0.3.2.dist-info/entry_points.txt
modernize_reporter-0.3.2.dist-info/top_level.txt
