Metadata-Version: 2.1
Name: modernize-reporter
Version: 0.3.2
Summary: Reports the modernization status for hybrid codebases.
Home-page: https://github.com/MartyMacGyver/python-modernize-reporter
Author: Martin Falatic
Author-email: martin@falatic.com
License: UNKNOWN
Platform: UNKNOWN
Classifier: License :: OSI Approved :: BSD License
Classifier: Programming Language :: Python
Classifier: Programming Language :: Python :: 2.6
Classifier: Programming Language :: Python :: 2.7
Classifier: Programming Language :: Python :: 3
Requires-Dist: modernize (>=0.6)
